MANIFEST.in
README.rst
setup.cfg
setup.py
django_microsip_catalogoarticulos/__init__.py
django_microsip_catalogoarticulos/__init__.pyc
django_microsip_catalogoarticulos/autocomplete_light_registry.pyc
django_microsip_catalogoarticulos/config.pyc
django_microsip_catalogoarticulos/forms.pyc
django_microsip_catalogoarticulos/models.pyc
django_microsip_catalogoarticulos/urls.pyc
django_microsip_catalogoarticulos/views.pyc
django_microsip_catalogoarticulos.egg-info/PKG-INFO
django_microsip_catalogoarticulos.egg-info/SOURCES.txt
django_microsip_catalogoarticulos.egg-info/dependency_links.txt
django_microsip_catalogoarticulos.egg-info/top_level.txt
django_microsip_catalogoarticulos/custom_db/__init__.py
django_microsip_catalogoarticulos/custom_db/__init__.pyc
django_microsip_catalogoarticulos/custom_db/procedures.py
django_microsip_catalogoarticulos/custom_db/procedures.pyc
django_microsip_catalogoarticulos/static/js/django_microsip_catalogoarticulos/tags.js
django_microsip_catalogoarticulos/templates/django_microsip_catalogoarticulos/articulo.html
django_microsip_catalogoarticulos/templates/django_microsip_catalogoarticulos/articulos.html
django_microsip_catalogoarticulos/templates/django_microsip_catalogoarticulos/base.html
django_microsip_catalogoarticulos/templates/django_microsip_catalogoarticulos/index.html
django_microsip_catalogoarticulos/templates/django_microsip_catalogoarticulos/precios.html
django_microsip_catalogoarticulos/templates/django_microsip_catalogoarticulos/tag.html
django_microsip_catalogoarticulos/templates/django_microsip_catalogoarticulos/tags.html